MANIFEST.in
README.rst
setup.py
Starbucks.egg-info/PKG-INFO
Starbucks.egg-info/SOURCES.txt
Starbucks.egg-info/dependency_links.txt
Starbucks.egg-info/entry_points.txt
Starbucks.egg-info/requires.txt
Starbucks.egg-info/top_level.txt
starbucks/__init__.py
starbucks/cli.py
starbucks/starbucks.py