Metadata-Version: 1.0
Name: Starbucks
Version: 0.2.2
Summary: Unoffical Starbucks API.
Home-page: https://github.com/minsoopark/starbucks-py
Author: Minsoo Park
Author-email: minsoo1003@gmail.com
License: BSD License
Keywords: Starbucks
Platform: UNKNOWN
